LICENSE
MANIFEST.in
README.md
setup.py
reddit_extract/__init__.py
reddit_extract/logger.py
reddit_extract/main.py
reddit_extract/process.py
reddit_extract/reddit.py
reddit_extract/utility.py
reddit_extract.egg-info/PKG-INFO
reddit_extract.egg-info/SOURCES.txt
reddit_extract.egg-info/dependency_links.txt
reddit_extract.egg-info/not-zip-safe
reddit_extract.egg-info/requires.txt
reddit_extract.egg-info/top_level.txt
reddit_extract/resources/search_template.txt