Metadata-Version: 2.1
Name: reddit-extract
Version: 0.2.0
Summary: Tool for extracting reddit comments
Home-page: https://github.com/dillonmabry/reddit-comments-tool
Author: Dillon Mabry
Author-email: rapid.dev.solutions@gmail.com
License: MIT
Platform: UNKNOWN
